[{"album": "狐妖小红娘·南国篇 动画原声大碟~众生~", "name": "众生", "author": "腾讯动漫", "lyric": "[by:GoodTM]\n[00:03.84]作词：HAKU\n[00:04.03]作曲：战场原妖精\n[00:04.26]伴唱：Sillian Wong\n[00:04.49]\n[00:28.56]花非花\n[00:29.28]我心如明镜\n[00:30.83]但睁眼亦庆幸\n[00:35.06]唯独我不可以发声\n[00:37.39]如顽强疾病与命格相衬\n[00:41.75]见众生因未见众生\n[00:43.99]以为这红尘\n[00:45.60]每个人都在等\n[00:47.85]慈悲命运皆是药引\n[00:50.67]人人极享受\n[00:52.32]为何失宠只得一个人\n[00:54.17]我发问\n[00:55.49]这众生\n[00:56.81]众生 于我掌声\n[01:00.23]却未予我身份\n[01:03.47]只能听闻未敢现身\n[01:06.82]哪怕想做傀儡身后亦无人\n[01:09.99]众生\n[01:12.05]与我相亲却不与我接近\n[01:16.65]谁的灵魂\n[01:18.43]暂借肉身\n[01:20.12]若没有爱侣\n[01:21.72]是谁在受困每句的过问\n[01:26.10]徒增我伤痕\n[01:29.62]\n[01:40.76]雾非雾\n[01:41.49]我何德何能\n[01:43.15]又因何而降生\n[01:47.36]唯独我不可以重生\n[01:49.77]如拿着把柄与自我抗争\n[01:54.03]见众生\n[01:54.81]因望见众生\n[01:56.42]方知这红尘其面目极可憎\n[02:00.73]世间恶行皆如诛骨\n[02:02.97]人人忙退让\n[02:05.07]为何有人却奋不顾身\n[02:06.54]我反咬\n[02:07.74]这众生\n[02:09.22]众生 不过分身仰仗他人点灯\n[02:15.86]俯身一吻 因爱无因\n[02:19.19]哪怕像这傀儡亦可以招魂\n[02:22.40]众生 一浮尘 我只贪欢不偷生\n[02:28.94]谁的泪痕 赠这缘分\n[02:32.37]哪怕千古罪 亦要爱一人\n[02:36.08]领不到教训\n[02:38.43]不做阶下臣\n[02:42.36]\n[03:05.18]众生 予我掌声却未予我身份\n[03:11.69]只能听闻 未敢现身\n[03:14.89]哪怕想做傀儡身后亦无人\n[03:18.28]众生 与我相亲却不与我接近\n[03:24.72]谁的灵魂 暂借肉身\n[03:28.42]若没有爱侣 是谁在受困\n[03:31.66]每句的过问 徒增我伤痕\n[03:39.04]\n", "id": 1335841605, "cmts": []}, {"album": "通灵妃动画原声大碟 霸道王爷虎王妃", "name": "宣泄", "author": "腾讯动漫", "lyric": "\n此歌曲为没有填词的纯音乐，请您欣赏\n", "id": 1329719224, "cmts": []}, {"album": "狐妖小红娘·竹业篇 动画原声大碟 前缘", "name": "一剑破云", "author": "腾讯动漫", "lyric": "\n此歌曲为没有填词的纯音乐，请您欣赏\n", "id": 1353010291, "cmts": []}, {"album": "通灵妃动画原声大碟 霸道王爷虎王妃", "name": "嘎嘎", "author": "腾讯动漫", "lyric": "[by:森川泷屿]\n[ti:嘎嘎 (《通灵妃》动画片头曲)]\n[ar:雷敏敏]\n[al:嘎嘎]\n[by:]\n[offset:0]\n[00:00.000] 作曲 : 广西巴托克\n[00:00.696] 作词 : Draceana\n[00:02.89]编曲：巴托哥\n[00:03.04]Rap：Wi-Hi-Fi\n[00:03.16]Rap作词：Draceana\n[00:03.29]词曲协力：凋寒\n[00:03.47]混音：巴托哥\n[00:03.63]监制：潇娘\n[00:04.69]山坡那边红花夕阳满天开\n[00:07.68]来个东边漂亮小妹儿家来哎嗨哟\n[00:11.19]伊儿呀嘿\n[00:12.52]瞧见红花含苞呀呼嘿\n[00:14.64]水灵灵的小骨朵嘛等着哥来采\n[00:18.17]月亮下山太阳还没爬上来 （嘎嘎）\n[00:21.44]小妹儿采着红花\n[00:22.54]好似月亮带露开（想吃肉嘎嘎）\n[00:25.07]伊儿呀嘿 （嘎嘎）\n[00:26.58]胭脂盖头啷个红裙头 （嘎嘎）\n[00:28.58]小妹儿大了\n[00:29.38]可有哥哥在心怀（想吃肉嘎嘎）\n[00:31.96]（北壮语）\n[00:32.56]今晚月亮红（含呢芒论另）\n[00:34.43]猴子去哪吃果（领贝裸哽麻）\n[00:38.58]水獭去哪吃鱼（拿贝裸哽怕）\n[00:41.96]吃完饭后（哽守意）\n[00:44.15]咱们去玩耍（送喽贝裸溜）\n[00:45.70]山坡那边红花夕阳满天开\n[00:48.54]来个东边漂亮小妹儿家来哎嗨哟\n[00:52.34]伊儿呀嘿\n[00:53.68]瞧见红花盛开呀呼嘿\n[00:55.76]明亮亮的小花苞嘛等着哥来采\n[00:59.20]月亮下山太阳还没爬上来\n[01:02.22]小妹儿采着红花好似田边小青麦\n[01:06.08]伊儿呀嘿\n[01:07.36]胭脂盖头啷个红裙头\n[01:09.48]小妹儿大了要有哥哥在心怀\n[01:12.94]溪水清清红花莲叶水中开\n[01:15.92]揉碎花瓣绞着心来支吾真难捱\n[01:19.78]伊儿呀嘿\n[01:21.07]听哥真心一句表白\n[01:23.21]莫让花儿伤心败哟伤心开\n[01:26.34]（北壮语）\n[01:27.00]今晚月亮红（含呢芒论另）\n[01:29.76]猴子去哪吃果（领贝裸哽麻）\n[01:32.81]水獭去哪吃鱼（拿贝裸哽怕）\n[01:36.63]吃完饭后（哽守意）\n[01:38.80]咱们去玩耍（送喽贝裸溜）\n[01:40.32]山坡那边红花夕阳满天开\n[01:43.36]来个东边漂亮小妹儿家来哎嗨哟\n[01:47.22]伊儿呀嘿\n[01:48.49]瞧见红花盛开呀呼嘿\n[01:50.64]明亮亮的小花苞嘛等着哥来采\n[01:54.18]月亮下山太阳还没爬上来\n[01:57.07]小妹儿采着红花好似田边小青麦\n[02:01.13]伊儿呀嘿\n[02:02.16]胭脂盖头啷个红裙头\n[02:04.32]小妹儿大了要有哥哥在心怀\n[02:07.82]溪水清清红花莲叶水中开\n[02:10.80]揉碎花瓣绞着心来支吾真难捱\n[02:14.59]伊儿呀嘿\n[02:15.88]听哥真心一句表白\n[02:18.04]莫让花儿伤心败哟伤心开\n[02:21.54]（北壮语）\n[02:22.13]今晚月亮红（含呢芒论另）\n[02:23.63]猴子去哪吃果（领贝裸哽麻）\n[02:27.83]水獭去哪吃鱼（拿贝裸哽怕）\n[02:31.20]吃完饭后（哽守意）\n[02:33.69]咱们去玩耍（送喽贝裸溜）\n[02:35.21]山坡那边红花夕阳满天开\n[02:38.20]来个东边漂亮小妹儿家来哎嗨哟\n[02:41.99]伊儿呀嘿\n[02:43.30]瞧见红花烂漫呀呼嘿\n[02:45.46]美艳艳的小花朵嘛等着哥来采\n[02:48.87]月亮下山太阳还没爬上来\n[02:51.89]小妹儿采着红花好似溪水夜中白\n[02:55.62]伊儿呀嘿\n[02:57.08]胭脂盖头啷个红裙头\n[02:59.20]小妹儿心里哥哥一直在心怀\n[03:02.33]Rap：\n[03:02.48]You just Dash my heart\n[03:03.51]You just Dash my heart\n[03:03.67]You just Dash my heart\n[03:03.82]You should better watch your way\n[03:04.44]Why you knock me in my face\n[03:05.78]I eat too much salty fish\n[03:07.36]So that I will miss you everyday\n[03:09.39]Do not explore what is this\n[03:10.80]Because this's my best advise\n[03:12.74]Come with me in this life\n[03:14.24]Dash dash eternal\n[03:14.75]Come come come become to a salty fish\n[03:16.77]Please help me watch this\n[03:18.03]Baby tell'em witch one is the real salty fish\n[03:19.79]Grouper sardine sole cero saury globefish\n[03:21.33]There's a salmon\n[03:21.96]Mango grow in summer day\n[03:22.60]You are my precious spotless Chinese chestnut in this wintertime\n[03:22.92]You're the psychedelic charming shrimp I can't totally deny\n[03:24.06]You have never been learned flute\n[03:25.32]But you can blow my heart puff\n[03:26.65]You make dizziness that I love you\n[03:27.84]You frame me love you cause carbohydrate overshoot\n[03:30.08]太阳不离满天红霞日光晒\n[03:33.07]染着小妹儿两颊好似胭脂堆满腮\n[03:36.94]伊儿呀嘿\n[03:38.18]凉风明月啷个兜里揣\n[03:40.36]想着哥哥溪边两个把脸挨\n[03:43.91]炮仗火把良辰花轿可迎来\n[03:46.73]红烛帐子好酒好菜把那宴席摆\n[03:50.67]伊儿呀嘿\n[03:51.87]胭脂盖头啷个红裙头\n[03:54.07]等着哥哥手忙脚乱来揭开\n[03:57.58]Rap：\n[03:57.79]Until we found love\n[03:59.26]Until we found love\n[04:01.20]Until we found love\n[04:02.68]Until we found love\n", "id": 1329719209, "cmts": []}, {"album": "狐妖小红娘·竹业篇 动画原声大碟 前缘", "name": "两情相悦", "author": "腾讯动漫", "lyric": "\n此歌曲为没有填词的纯音乐，请您欣赏\n", "id": 1353010292, "cmts": []}, {"album": "狐妖小红娘·南国篇 动画原声大碟~众生~", "name": "迷阵", "author": "腾讯动漫", "lyric": "", "id": 1335841606, "cmts": []}, {"album": "狐妖小红娘·竹业篇 动画原声大碟 前缘", "name": "危险迫近", "author": "腾讯动漫", "lyric": "\n此歌曲为没有填词的纯音乐，请您欣赏\n", "id": 1353010293, "cmts": []}, {"album": "狐妖小红娘·南国篇 动画原声大碟~众生~", "name": "围城", "author": "腾讯动漫", "lyric": "", "id": 1335841607, "cmts": []}, {"album": "狐妖小红娘·竹业篇 动画原声大碟 前缘", "name": "大干一场", "author": "腾讯动漫", "lyric": "\n此歌曲为没有填词的纯音乐，请您欣赏\n", "id": 1353010294, "cmts": []}, {"album": "狐妖小红娘·南国篇 动画原声大碟~众生~", "name": "愿我", "author": "腾讯动漫", "lyric": "", "id": 1335841608, "cmts": []}, {"album": "狐妖小红娘·竹业篇 动画原声大碟 前缘", "name": "尽入彀中", "author": "腾讯动漫", "lyric": "\n此歌曲为没有填词的纯音乐，请您欣赏\n", "id": 1353010295, "cmts": []}, {"album": "狐妖小红娘·竹业篇 动画原声大碟 前缘", "name": "山雨欲来", "author": "腾讯动漫", "lyric": "\n此歌曲为没有填词的纯音乐，请您欣赏\n", "id": 1353010296, "cmts": []}, {"album": "通灵妃动画原声大碟 霸道王爷虎王妃", "name": "沉思", "author": "腾讯动漫", "lyric": "\n此歌曲为没有填词的纯音乐，请您欣赏\n", "id": 1329719214, "cmts": []}, {"album": "狐妖小红娘·竹业篇 动画原声大碟 前缘", "name": "晴空邂逅", "author": "腾讯动漫", "lyric": "\n此歌曲为没有填词的纯音乐，请您欣赏\n", "id": 1353010297, "cmts": []}, {"album": "通灵妃动画原声大碟 霸道王爷虎王妃", "name": "答非所问", "author": "腾讯动漫", "lyric": "\n此歌曲为没有填词的纯音乐，请您欣赏\n", "id": 1329719215, "cmts": []}, {"album": "狐妖小红娘·竹业篇 动画原声大碟 前缘", "name": "暗夜行舟", "author": "腾讯动漫", "lyric": "\n此歌曲为没有填词的纯音乐，请您欣赏\n", "id": 1353010298, "cmts": []}, {"album": "通灵妃动画原声大碟 霸道王爷虎王妃", "name": "尴尬", "author": "腾讯动漫", "lyric": "\n此歌曲为没有填词的纯音乐，请您欣赏\n", "id": 1329719216, "cmts": []}, {"album": "狐妖小红娘·竹业篇 动画原声大碟 前缘", "name": "沂水弦歌", "author": "腾讯动漫", "lyric": "\n此歌曲为没有填词的纯音乐，请您欣赏\n", "id": 1353010299, "cmts": []}, {"album": "通灵妃动画原声大碟 霸道王爷虎王妃", "name": "感怀", "author": "腾讯动漫", "lyric": "\n此歌曲为没有填词的纯音乐，请您欣赏\n", "id": 1329719217, "cmts": []}, {"album": "狐妖小红娘·竹业篇 动画原声大碟 前缘", "name": "荒无人烟", "author": "腾讯动漫", "lyric": "\n此歌曲为没有填词的纯音乐，请您欣赏\n", "id": 1353010300, "cmts": []}, {"album": "通灵妃动画原声大碟 霸道王爷虎王妃", "name": "辉", "author": "腾讯动漫", "lyric": "\n此歌曲为没有填词的纯音乐，请您欣赏\n", "id": 1329719218, "cmts": []}, {"album": "狐妖小红娘·南国篇 动画原声大碟~众生~", "name": "毒公子", "author": "腾讯动漫", "lyric": "\n此歌曲为没有填词的纯音乐，请您欣赏\n", "id": 1335841614, "cmts": []}, {"album": "狐妖小红娘·竹业篇 动画原声大碟 前缘", "name": "黄雀在后", "author": "腾讯动漫", "lyric": "\n此歌曲为没有填词的纯音乐，请您欣赏\n", "id": 1353010301, "cmts": []}, {"album": "通灵妃动画原声大碟 霸道王爷虎王妃", "name": "景", "author": "腾讯动漫", "lyric": "\n此歌曲为没有填词的纯音乐，请您欣赏\n", "id": 1329719219, "cmts": []}, {"album": "通灵妃动画原声大碟 霸道王爷虎王妃", "name": "破", "author": "腾讯动漫", "lyric": "\n此歌曲为没有填词的纯音乐，请您欣赏\n", "id": 1329719220, "cmts": []}, {"album": "狐妖小红娘·南国篇 动画原声大碟~众生~", "name": "老毒王", "author": "腾讯动漫", "lyric": "\n此歌曲为没有填词的纯音乐，请您欣赏\n", "id": 1335841616, "cmts": []}, {"album": "通灵妃动画原声大碟 霸道王爷虎王妃", "name": "情深缘浅", "author": "腾讯动漫", "lyric": "\n此歌曲为没有填词的纯音乐，请您欣赏\n", "id": 1329719221, "cmts": []}, {"album": "狐妖小红娘·南国篇 动画原声大碟~众生~", "name": "慢搞笑", "author": "腾讯动漫", "lyric": "\n此歌曲为没有填词的纯音乐，请您欣赏\n", "id": 1335841617, "cmts": []}, {"album": "通灵妃动画原声大碟 霸道王爷虎王妃", "name": "跳戏", "author": "腾讯动漫", "lyric": "\n此歌曲为没有填词的纯音乐，请您欣赏\n", "id": 1329719222, "cmts": []}, {"album": "狐妖小红娘·南国篇 动画原声大碟~众生~", "name": "南国风情", "author": "腾讯动漫", "lyric": "\n此歌曲为没有填词的纯音乐，请您欣赏\n", "id": 1335841618, "cmts": []}, {"album": "通灵妃动画原声大碟 霸道王爷虎王妃", "name": "望", "author": "腾讯动漫", "lyric": "\n此歌曲为没有填词的纯音乐，请您欣赏\n", "id": 1329719223, "cmts": []}, {"album": "狐妖小红娘·南国篇 动画原声大碟~众生~", "name": "平丘月初", "author": "腾讯动漫", "lyric": "\n此歌曲为没有填词的纯音乐，请您欣赏\n", "id": 1335841619, "cmts": []}, {"album": "狐妖小红娘·南国篇 动画原声大碟~众生~", "name": "平丘月初战斗", "author": "腾讯动漫", "lyric": "\n此歌曲为没有填词的纯音乐，请您欣赏\n", "id": 1335841620, "cmts": []}, {"album": "通灵妃动画原声大碟 霸道王爷虎王妃", "name": "游", "author": "腾讯动漫", "lyric": "\n此歌曲为没有填词的纯音乐，请您欣赏\n", "id": 1329719225, "cmts": []}, {"album": "狐妖小红娘·南国篇 动画原声大碟~众生~", "name": "甜蜜的回忆", "author": "腾讯动漫", "lyric": "\n此歌曲为没有填词的纯音乐，请您欣赏\n", "id": 1335841621, "cmts": []}, {"album": "通灵妃动画原声大碟 霸道王爷虎王妃", "name": "遇见", "author": "腾讯动漫", "lyric": "\n此歌曲为没有填词的纯音乐，请您欣赏\n", "id": 1329719226, "cmts": []}, {"album": "通灵妃动画原声大碟 霸道王爷虎王妃", "name": "镇", "author": "腾讯动漫", "lyric": "\n此歌曲为没有填词的纯音乐，请您欣赏\n", "id": 1329719227, "cmts": []}, {"album": "通灵妃动画原声大碟 霸道王爷虎王妃", "name": "争", "author": "腾讯动漫", "lyric": "\n此歌曲为没有填词的纯音乐，请您欣赏\n", "id": 1329719228, "cmts": []}, {"album": "狐妖小红娘·南国篇 动画原声大碟~众生~", "name": "巫皇山", "author": "腾讯动漫", "lyric": "\n此歌曲为没有填词的纯音乐，请您欣赏\n", "id": 1335841624, "cmts": []}, {"album": "狐妖小红娘·月红篇 动画原声大碟 七夕", "name": "成为一只真正的狐妖", "author": "腾讯动漫", "lyric": "[00:00:00]此歌曲为没有填词的纯音乐，请您欣赏\n", "id": 1382765834, "cmts": []}, {"album": "狐妖小红娘·南国篇 动画原声大碟~众生~", "name": "走火入魔", "author": "腾讯动漫", "lyric": "\n此歌曲为没有填词的纯音乐，请您欣赏\n", "id": 1335841625, "cmts": []}, {"album": "狐妖小红娘·月红篇 动画原声大碟 七夕", "name": "绝对零度", "author": "腾讯动漫", "lyric": "[00:00:00]此歌曲为没有填词的纯音乐，请您欣赏\n", "id": 1382765835, "cmts": []}, {"album": "猫妖的诱惑 动画配乐~忆前尘~", "name": "落花赋", "author": "腾讯动漫", "lyric": "", "id": 1361391551, "cmts": []}, {"album": "狐妖小红娘·月红篇 动画原声大碟 七夕", "name": "盛怒的前兆", "author": "腾讯动漫", "lyric": "[00:00:00]此歌曲为没有填词的纯音乐，请您欣赏\n", "id": 1382765836, "cmts": []}, {"album": "猫妖的诱惑 动画配乐~忆前尘~", "name": "苍月啼", "author": "腾讯动漫", "lyric": "", "id": 1361394188, "cmts": []}, {"album": "狐妖小红娘·月红篇 动画原声大碟 七夕", "name": "东方月初", "author": "腾讯动漫", "lyric": "[00:00:00]此歌曲为没有填词的纯音乐，请您欣赏\n", "id": 1382765846, "cmts": []}]